CHANGES.txt
LICENSE.txt
MANIFEST.in
README.txt
setup.py
js/__init__.py
js.swfobject.egg-info/PKG-INFO
js.swfobject.egg-info/SOURCES.txt
js.swfobject.egg-info/dependency_links.txt
js.swfobject.egg-info/entry_points.txt
js.swfobject.egg-info/namespace_packages.txt
js.swfobject.egg-info/not-zip-safe
js.swfobject.egg-info/requires.txt
js.swfobject.egg-info/top_level.txt
js/swfobject/__init__.py
js/swfobject/test_swfobject.txt
js/swfobject/resources/README.txt
js/swfobject/resources/swfobject.js