Metadata-Version: 1.0
Name: js.swfobject
Version: 2.2
Summary: Fanstatic packaging of SWFObject
Home-page: UNKNOWN
Author: Fanstatic Developers
Author-email: fanstatic@googlegroups.com
License: BSD
Platform: UNKNOWN
